descriptor_di/__about__.py
descriptor_di/__init__.py
descriptor_di-0.1.0.dist-info/METADATA
descriptor_di-0.1.0.dist-info/WHEEL
descriptor_di-0.1.0.dist-info/licenses/LICENSE.txt
descriptor_di-0.1.0.dist-info/RECORD
